LICENSE
MANIFEST.in
README.md
setup.py
pytools123456789/__init__.py
pytools123456789/github_api.py
pytools123456789.egg-info/PKG-INFO
pytools123456789.egg-info/SOURCES.txt
pytools123456789.egg-info/dependency_links.txt
pytools123456789.egg-info/not-zip-safe
pytools123456789.egg-info/requires.txt
pytools123456789.egg-info/top_level.txt